README.md
setup.cfg
setup.py
bin/spin.py
cpuspinner/__init__.py
cpuspinner.egg-info/PKG-INFO
cpuspinner.egg-info/SOURCES.txt
cpuspinner.egg-info/dependency_links.txt
cpuspinner.egg-info/top_level.txt