Metadata-Version: 1.0
Name: cpuspinner
Version: 0.1
Summary: A background thread spinning your cpu at 100%
Home-page: https://github.com/posix4e/cpuspinner
Author: Alex Newman
Author-email: posix4e@gmail.com
License: UNKNOWN
Keywords: testing
Platform: UNKNOWN
